PyTac3D/Analyzer.py
PyTac3D/Data.py
PyTac3D/Displayer.py
PyTac3D/ErrorMessage.py
PyTac3D/GUI.py
PyTac3D/GUI_Displayer.py
PyTac3D/Manager.py
PyTac3D/Presets.py
PyTac3D/Sensor.py
PyTac3D/__init__.py
PyTac3D/cli.py
PyTac3D/example/analyze_frame_data.py
PyTac3D/example/get_contact_info.py
PyTac3D/example/get_force_and_displacement_data.py
PyTac3D/example/get_object_info.py
PyTac3D/example/load_data_1.py
PyTac3D/example/load_data_2.py
PyTac3D/example/processor_configure.py
PyTac3D/example/processor_start_sensor.py
PyTac3D/example/processor_stop_sensor.py
PyTac3D/example/real_time_object_detect.py
PyTac3D/example/receive_and_record_data_using_callback.py
PyTac3D/example/receive_from_multiple_sensors.py
PyTac3D/example/receive_from_single_sensor.py
PyTac3D/example/smoother_mesh.py
PyTac3D/example_data/example_1/AD2-0065L/3D_Displacements.npy
PyTac3D/example_data/example_1/AD2-0065L/3D_Forces.npy
PyTac3D/example_data/example_1/AD2-0065L/3D_Normals.npy
PyTac3D/example_data/example_1/AD2-0065L/3D_Positions.npy
PyTac3D/example_data/example_1/AD2-0065L/3D_ResultantForce.npy
PyTac3D/example_data/example_1/AD2-0065L/3D_ResultantMoment.npy
PyTac3D/example_data/example_1/AD2-0065L/index.npy
PyTac3D/example_data/example_1/AD2-0065L/recvTimestamp.npy
PyTac3D/example_data/example_1/AD2-0065L/sendTimestamp.npy
PyTac3D/example_data/example_2/HDL1-GWH0021/3D_Displacements.npy
PyTac3D/example_data/example_2/HDL1-GWH0021/3D_Forces.npy
PyTac3D/example_data/example_2/HDL1-GWH0021/3D_Positions.npy
PyTac3D/example_data/example_2/HDL1-GWH0021/3D_ResultantForce.npy
PyTac3D/example_data/example_2/HDL1-GWH0021/3D_ResultantMoment.npy
PyTac3D/example_data/example_2/HDL1-GWH0021/index.npy
PyTac3D/example_data/example_2/HDL1-GWH0021/overview.csv
PyTac3D/example_data/example_2/HDL1-GWH0021/sendTimestamp.npy
PyTac3D/example_data/example_2/HDL1-GWH0022/3D_Displacements.npy
PyTac3D/example_data/example_2/HDL1-GWH0022/3D_Forces.npy
PyTac3D/example_data/example_2/HDL1-GWH0022/3D_Positions.npy
pytac3d-3.3.0.8.dist-info/METADATA
pytac3d-3.3.0.8.dist-info/WHEEL
pytac3d-3.3.0.8.dist-info/entry_points.txt
pytac3d-3.3.0.8.dist-info/top_level.txt
pytac3d-3.3.0.8.dist-info/RECORD
