Metadata-Version: 2.4
Name: PyTac3D
Version: 3.3.0.8
Summary: Tac3D sensor interface
Author-email: Lunwei Zhang <sxhzzlw@126.com>
Requires-Python: <3.12,>=3.8
Requires-Dist: vtk==9.3.1
Requires-Dist: opencv-python>=4.7.0
Requires-Dist: ruamel.yaml==0.18.10
Requires-Dist: vedo==2023.4.6
Requires-Dist: netifaces2==0.0.22
Requires-Dist: scipy
Requires-Dist: appdirs
Requires-Dist: requests
Requires-Dist: tqdm
